glue_vispy_viewers/__init__.py
glue_vispy_viewers/conftest.py
glue_vispy_viewers/utils.py
glue_vispy_viewers/common/__init__.py
glue_vispy_viewers/common/axes.py
glue_vispy_viewers/common/compat.py
glue_vispy_viewers/common/glue_point.png
glue_vispy_viewers/common/glue_rotate.png
glue_vispy_viewers/common/layer_artist.py
glue_vispy_viewers/common/layer_state.py
glue_vispy_viewers/common/selection_tools.py
glue_vispy_viewers/common/toolbar.py
glue_vispy_viewers/common/tools.py
glue_vispy_viewers/common/viewer_state.py
glue_vispy_viewers/common/vispy_data_viewer.py
glue_vispy_viewers/common/vispy_widget.py
glue_vispy_viewers/common/jupyter/__init__.py
glue_vispy_viewers/common/jupyter/data_viewer.py
glue_vispy_viewers/common/jupyter/toolbar.py
glue_vispy_viewers/common/qt/__init__.py
glue_vispy_viewers/common/qt/data_viewer.py
glue_vispy_viewers/common/qt/glue_record_start.png
glue_vispy_viewers/common/qt/glue_record_stop.png
glue_vispy_viewers/common/qt/toolbar.py
glue_vispy_viewers/common/qt/tools.py
glue_vispy_viewers/common/qt/viewer_options.py
glue_vispy_viewers/common/qt/viewer_options.ui
glue_vispy_viewers/common/qt/tests/__init__.py
glue_vispy_viewers/common/qt/tests/test_vispy_toolbar.py
glue_vispy_viewers/common/qt/tests/test_vispy_viewer.py
glue_vispy_viewers/common/tests/__init__.py
glue_vispy_viewers/common/tests/test_3d_axis_visual.py
glue_vispy_viewers/common/tests/test_vispy_widget.py
glue_vispy_viewers/compat/__init__.py
glue_vispy_viewers/compat/axis.py
glue_vispy_viewers/compat/text.py
glue_vispy_viewers/qt/__init__.py
glue_vispy_viewers/qt/tests/__init__.py
glue_vispy_viewers/qt/tests/test_session_back_compat.py
glue_vispy_viewers/qt/tests/data/__init__.py
glue_vispy_viewers/qt/tests/data/multiple_volumes_v1.glu
glue_vispy_viewers/qt/tests/data/multiple_volumes_v2.glu
glue_vispy_viewers/qt/tests/data/scatter_volume_selection.glu
glue_vispy_viewers/qt/tests/data/scatter_volume_v0.glu
glue_vispy_viewers/qt/tests/data/scatter_volume_v1.glu
glue_vispy_viewers-1.2.3.dist-info/licenses/LICENSE
glue_vispy_viewers-1.2.3.dist-info/METADATA
glue_vispy_viewers-1.2.3.dist-info/WHEEL
glue_vispy_viewers-1.2.3.dist-info/entry_points.txt
glue_vispy_viewers-1.2.3.dist-info/top_level.txt
glue_vispy_viewers-1.2.3.dist-info/zip-safe
glue_vispy_viewers-1.2.3.dist-info/RECORD
