Metadata-Version: 2.4
Name: glue-vispy-viewers
Version: 1.2.3
Summary: Vispy-based viewers for Glue
Home-page: https://github.com/glue-viz/glue-3d-viewer
Author: Thomas Robitaille, Penny Qian, and Maxwell Tsai
Author-email: glueviz@gmail.com
Requires-Python: >=3.8
License-File: LICENSE
Requires-Dist: numpy
Requires-Dist: pyopengl
Requires-Dist: glue-core>=1.13.1
Requires-Dist: echo>=0.6
Requires-Dist: scipy
Requires-Dist: matplotlib
Requires-Dist: vispy>=0.12.0
Requires-Dist: importlib_metadata>=3.6; python_version < "3.10"
Requires-Dist: glfw
Requires-Dist: imageio
Provides-Extra: test
Requires-Dist: pytest; extra == "test"
Requires-Dist: pytest-cov; extra == "test"
Requires-Dist: pytest-faulthandler; extra == "test"
Requires-Dist: objgraph; sys_platform != "win32" and extra == "test"
Requires-Dist: mock; extra == "test"
Provides-Extra: pyqt
Requires-Dist: qtpy; extra == "pyqt"
Requires-Dist: glue-qt>=0.1.0; extra == "pyqt"
Requires-Dist: PyQt6; extra == "pyqt"
Provides-Extra: pyside
Requires-Dist: qtpy; extra == "pyside"
Requires-Dist: glue-qt>=0.1.0; extra == "pyside"
Requires-Dist: PySide6; extra == "pyside"
Provides-Extra: jupyter
Requires-Dist: glue-jupyter; extra == "jupyter"
Requires-Dist: jupyter_rfb; extra == "jupyter"
Dynamic: license-file
